{
  "CF103709397": {
    "contest_id": 1287,
    "language": "GNU C++17",
    "path": "codeforces/1287/B.cpp",
    "platform": "Codeforces",
    "problem_index": "B",
    "problem_name": "Hyperset",
    "problem_url": "https://codeforces.com/contest/1287/problem/B",
    "submission_id": "CF103709397",
    "submission_url": "https://codeforces.com/contest/1287/submission/103709397",
    "tags": [
      "brute force",
      "data structures",
      "implementation",
      "*1500"
    ],
    "timestamp": "Jan/08/2021 17:01"
  },
  "CF103712933": {
    "contest_id": 1201,
    "language": "GNU C++17",
    "path": "codeforces/1201/B.cpp",
    "platform": "Codeforces",
    "problem_index": "B",
    "problem_name": "Zero Array",
    "problem_url": "https://codeforces.com/contest/1201/problem/B",
    "submission_id": "CF103712933",
    "submission_url": "https://codeforces.com/contest/1201/submission/103712933",
    "tags": [
      "greedy",
      "math",
      "*1500"
    ],
    "timestamp": "Jan/08/2021 17:46"
  },
  "CF103720907": {
    "contest_id": 235,
    "language": "GNU C++17",
    "path": "codeforces/235/A.cpp",
    "platform": "Codeforces",
    "problem_index": "A",
    "problem_name": "LCM Challenge",
    "problem_url": "https://codeforces.com/contest/235/problem/A",
    "submission_id": "CF103720907",
    "submission_url": "https://codeforces.com/contest/235/submission/103720907",
    "tags": [
      "number theory",
      "*1600"
    ],
    "timestamp": "Jan/08/2021 19:18"
  },
  "CF103741640": {
    "contest_id": 1467,
    "language": "GNU C++17",
    "path": "codeforces/1467/A.cpp",
    "platform": "Codeforces",
    "problem_index": "A",
    "problem_name": "Wizard of Orz",
    "problem_url": "https://codeforces.com/contest/1467/problem/A",
    "submission_id": "CF103741640",
    "submission_url": "https://codeforces.com/contest/1467/submission/103741640",
    "tags": [
      "constructive algorithms",
      "greedy",
      "math",
      "*900"
    ],
    "timestamp": "Jan/08/2021 20:20"
  },
  "CF103825388": {
    "contest_id": 1467,
    "language": "GNU C++17",
    "path": "codeforces/1467/B.cpp",
    "platform": "Codeforces",
    "problem_index": "B",
    "problem_name": "Hills And Valleys",
    "problem_url": "https://codeforces.com/contest/1467/problem/B",
    "submission_id": "CF103825388",
    "submission_url": "https://codeforces.com/contest/1467/submission/103825388",
    "tags": [
      "brute force",
      "implementation",
      "*1700"
    ],
    "timestamp": "Jan/09/2021 00:55"
  },
  "CF103857563": {
    "contest_id": 1467,
    "language": "GNU C++17",
    "path": "codeforces/1467/C.cpp",
    "platform": "Codeforces",
    "problem_index": "C",
    "problem_name": "Three Bags",
    "problem_url": "https://codeforces.com/contest/1467/problem/C",
    "submission_id": "CF103857563",
    "submission_url": "https://codeforces.com/contest/1467/submission/103857563",
    "tags": [
      "constructive algorithms",
      "greedy",
      "*1900"
    ],
    "timestamp": "Jan/09/2021 13:18"
  },
  "CF103861725": {
    "contest_id": 1363,
    "language": "GNU C++17",
    "path": "codeforces/1363/C.cpp",
    "platform": "Codeforces",
    "problem_index": "C",
    "problem_name": "Game On Leaves",
    "problem_url": "https://codeforces.com/contest/1363/problem/C",
    "submission_id": "CF103861725",
    "submission_url": "https://codeforces.com/contest/1363/submission/103861725",
    "tags": [
      "games",
      "trees",
      "*1600"
    ],
    "timestamp": "Jan/09/2021 14:01"
  },
  "CF103930706": {
    "contest_id": 1348,
    "language": "GNU C++17",
    "path": "codeforces/1348/C.cpp",
    "platform": "Codeforces",
    "problem_index": "C",
    "problem_name": "Phoenix and Distribution",
    "problem_url": "https://codeforces.com/contest/1348/problem/C",
    "submission_id": "CF103930706",
    "submission_url": "https://codeforces.com/contest/1348/submission/103930706",
    "tags": [
      "constructive algorithms",
      "greedy",
      "sortings",
      "strings",
      "*1600"
    ],
    "timestamp": "Jan/10/2021 11:00"
  },
  "CF103939238": {
    "contest_id": 1327,
    "language": "GNU C++17",
    "path": "codeforces/1327/C.cpp",
    "platform": "Codeforces",
    "problem_index": "C",
    "problem_name": "Game with Chips",
    "problem_url": "https://codeforces.com/contest/1327/problem/C",
    "submission_id": "CF103939238",
    "submission_url": "https://codeforces.com/contest/1327/submission/103939238",
    "tags": [
      "constructive algorithms",
      "implementation",
      "*1600"
    ],
    "timestamp": "Jan/10/2021 13:29"
  },
  "CF103975459": {
    "contest_id": 1389,
    "language": "GNU C++17",
    "path": "codeforces/1389/B.cpp",
    "platform": "Codeforces",
    "problem_index": "B",
    "problem_name": "Array Walk",
    "problem_url": "https://codeforces.com/contest/1389/problem/B",
    "submission_id": "CF103975459",
    "submission_url": "https://codeforces.com/contest/1389/submission/103975459",
    "tags": [
      "brute force",
      "dp",
      "greedy",
      "*1600"
    ],
    "timestamp": "Jan/10/2021 21:56"
  },
  "CF104003136": {
    "contest_id": 1251,
    "language": "GNU C++17",
    "path": "codeforces/1251/C.cpp",
    "platform": "Codeforces",
    "problem_index": "C",
    "problem_name": "Minimize The Integer",
    "problem_url": "https://codeforces.com/contest/1251/problem/C",
    "submission_id": "CF104003136",
    "submission_url": "https://codeforces.com/contest/1251/submission/104003136",
    "tags": [
      "greedy",
      "two pointers",
      "*1600"
    ],
    "timestamp": "Jan/11/2021 10:05"
  },
  "CF104011267": {
    "contest_id": 1165,
    "language": "GNU C++17",
    "path": "codeforces/1165/D.cpp",
    "platform": "Codeforces",
    "problem_index": "D",
    "problem_name": "Almost All Divisors",
    "problem_url": "https://codeforces.com/contest/1165/problem/D",
    "submission_id": "CF104011267",
    "submission_url": "https://codeforces.com/contest/1165/submission/104011267",
    "tags": [
      "math",
      "number theory",
      "*1600"
    ],
    "timestamp": "Jan/11/2021 12:40"
  },
  "CF104127402": {
    "contest_id": 228,
    "language": "GNU C++17",
    "path": "codeforces/228/A.cpp",
    "platform": "Codeforces",
    "problem_index": "A",
    "problem_name": "Is your horseshoe on the other hoof?",
    "problem_url": "https://codeforces.com/contest/228/problem/A",
    "submission_id": "CF104127402",
    "submission_url": "https://codeforces.com/contest/228/submission/104127402",
    "tags": [
      "implementation",
      "*800"
    ],
    "timestamp": "Jan/12/2021 21:16"
  },
  "CF104200471": {
    "contest_id": 510,
    "language": "GNU C++17",
    "path": "codeforces/510/A.cpp",
    "platform": "Codeforces",
    "problem_index": "A",
    "problem_name": "Fox And Snake",
    "problem_url": "https://codeforces.com/contest/510/problem/A",
    "submission_id": "CF104200471",
    "submission_url": "https://codeforces.com/contest/510/submission/104200471",
    "tags": [
      "implementation",
      "*800"
    ],
    "timestamp": "Jan/13/2021 19:38"
  },
  "CF104282385": {
    "contest_id": 1473,
    "language": "GNU C++17",
    "path": "codeforces/1473/A.cpp",
    "platform": "Codeforces",
    "problem_index": "A",
    "problem_name": "Replacing Elements",
    "problem_url": "https://codeforces.com/contest/1473/problem/A",
    "submission_id": "CF104282385",
    "submission_url": "https://codeforces.com/contest/1473/submission/104282385",
    "tags": [
      "greedy",
      "implementation",
      "math",
      "sortings",
      "*800"
    ],
    "timestamp": "Jan/14/2021 20:08"
  },
  "CF104300564": {
    "contest_id": 1473,
    "language": "GNU C++17",
    "path": "codeforces/1473/B.cpp",
    "platform": "Codeforces",
    "problem_index": "B",
    "problem_name": "String LCM",
    "problem_url": "https://codeforces.com/contest/1473/problem/B",
    "submission_id": "CF104300564",
    "submission_url": "https://codeforces.com/contest/1473/submission/104300564",
    "tags": [
      "brute force",
      "math",
      "number theory",
      "strings",
      "*1000"
    ],
    "timestamp": "Jan/14/2021 20:27"
  },
  "CF104327153": {
    "contest_id": 1473,
    "language": "GNU C++17",
    "path": "codeforces/1473/C.cpp",
    "platform": "Codeforces",
    "problem_index": "C",
    "problem_name": "No More Inversions",
    "problem_url": "https://codeforces.com/contest/1473/problem/C",
    "submission_id": "CF104327153",
    "submission_url": "https://codeforces.com/contest/1473/submission/104327153",
    "tags": [
      "constructive algorithms",
      "math",
      "*1500"
    ],
    "timestamp": "Jan/14/2021 21:19"
  },
  "CF104349948": {
    "contest_id": 1473,
    "language": "GNU C++17",
    "path": "codeforces/1473/D.cpp",
    "platform": "Codeforces",
    "problem_index": "D",
    "problem_name": "Program",
    "problem_url": "https://codeforces.com/contest/1473/problem/D",
    "submission_id": "CF104349948",
    "submission_url": "https://codeforces.com/contest/1473/submission/104349948",
    "tags": [
      "data structures",
      "dp",
      "implementation",
      "strings",
      "*1700"
    ],
    "timestamp": "Jan/14/2021 22:14"
  },
  "CF104350083": {
    "contest_id": 1473,
    "language": "GNU C++17",
    "path": "codeforces/1473/D.cpp",
    "platform": "Codeforces",
    "problem_index": "D",
    "problem_name": "Program",
    "problem_url": "https://codeforces.com/contest/1473/problem/D",
    "submission_id": "CF104350083",
    "submission_url": "https://codeforces.com/contest/1473/submission/104350083",
    "tags": [
      "data structures",
      "dp",
      "implementation",
      "strings",
      "*1700"
    ],
    "timestamp": "Jan/14/2021 22:15"
  },
  "CF104430489": {
    "contest_id": 1472,
    "language": "GNU C++17",
    "path": "codeforces/1472/E.cpp",
    "platform": "Codeforces",
    "problem_index": "E",
    "problem_name": "Correct Placement",
    "problem_url": "https://codeforces.com/contest/1472/problem/E",
    "submission_id": "CF104430489",
    "submission_url": "https://codeforces.com/contest/1472/submission/104430489",
    "tags": [
      "binary search",
      "data structures",
      "dp",
      "sortings",
      "two pointers",
      "*1700"
    ],
    "timestamp": "Jan/15/2021 21:41"
  },
  "CF104493431": {
    "contest_id": 1462,
    "language": "GNU C++17",
    "path": "codeforces/1462/F.cpp",
    "platform": "Codeforces",
    "problem_index": "F",
    "problem_name": "The Treasure of The Segments",
    "problem_url": "https://codeforces.com/contest/1462/problem/F",
    "submission_id": "CF104493431",
    "submission_url": "https://codeforces.com/contest/1462/submission/104493431",
    "tags": [
      "binary search",
      "data structures",
      "greedy",
      "*1800"
    ],
    "timestamp": "Jan/16/2021 15:07"
  },
  "CF104562323": {
    "contest_id": 1301,
    "language": "GNU C++17",
    "path": "codeforces/1301/B.cpp",
    "platform": "Codeforces",
    "problem_index": "B",
    "problem_name": "Motarack's Birthday",
    "problem_url": "https://codeforces.com/contest/1301/problem/B",
    "submission_id": "CF104562323",
    "submission_url": "https://codeforces.com/contest/1301/submission/104562323",
    "tags": [
      "binary search",
      "greedy",
      "ternary search",
      "*1500"
    ],
    "timestamp": "Jan/17/2021 12:45"
  },
  "CF104651681": {
    "contest_id": 20,
    "language": "GNU C++17",
    "path": "codeforces/20/C.cpp",
    "platform": "Codeforces",
    "problem_index": "C",
    "problem_name": "Dijkstra?",
    "problem_url": "https://codeforces.com/contest/20/problem/C",
    "submission_id": "CF104651681",
    "submission_url": "https://codeforces.com/contest/20/submission/104651681",
    "tags": [
      "graphs",
      "shortest paths",
      "*1900"
    ],
    "timestamp": "Jan/18/2021 12:59"
  },
  "CF104664729": {
    "contest_id": 1398,
    "language": "GNU C++17",
    "path": "codeforces/1398/C.cpp",
    "platform": "Codeforces",
    "problem_index": "C",
    "problem_name": "Good Subarrays",
    "problem_url": "https://codeforces.com/contest/1398/problem/C",
    "submission_id": "CF104664729",
    "submission_url": "https://codeforces.com/contest/1398/submission/104664729",
    "tags": [
      "data structures",
      "dp",
      "math",
      "*1600"
    ],
    "timestamp": "Jan/18/2021 14:36"
  },
  "CF104672368": {
    "contest_id": 1344,
    "language": "GNU C++17",
    "path": "codeforces/1344/A.cpp",
    "platform": "Codeforces",
    "problem_index": "A",
    "problem_name": "Hilbert's Hotel",
    "problem_url": "https://codeforces.com/contest/1344/problem/A",
    "submission_id": "CF104672368",
    "submission_url": "https://codeforces.com/contest/1344/submission/104672368",
    "tags": [
      "math",
      "number theory",
      "sortings",
      "*1600"
    ],
    "timestamp": "Jan/18/2021 15:41"
  },
  "CF104756293": {
    "contest_id": 799,
    "language": "GNU C++17",
    "path": "codeforces/799/B.cpp",
    "platform": "Codeforces",
    "problem_index": "B",
    "problem_name": "T-shirt buying",
    "problem_url": "https://codeforces.com/contest/799/problem/B",
    "submission_id": "CF104756293",
    "submission_url": "https://codeforces.com/contest/799/submission/104756293",
    "tags": [
      "data structures",
      "implementation",
      "*1400"
    ],
    "timestamp": "Jan/19/2021 16:02"
  },
  "CF104775745": {
    "contest_id": 1474,
    "language": "GNU C++17",
    "path": "codeforces/1474/A.cpp",
    "platform": "Codeforces",
    "problem_index": "A",
    "problem_name": "Puzzle From the Future",
    "problem_url": "https://codeforces.com/contest/1474/problem/A",
    "submission_id": "CF104775745",
    "submission_url": "https://codeforces.com/contest/1474/submission/104775745",
    "tags": [
      "greedy",
      "*800"
    ],
    "timestamp": "Jan/19/2021 20:13"
  },
  "CF104788892": {
    "contest_id": 1474,
    "language": "GNU C++17",
    "path": "codeforces/1474/B.cpp",
    "platform": "Codeforces",
    "problem_index": "B",
    "problem_name": "Different Divisors",
    "problem_url": "https://codeforces.com/contest/1474/problem/B",
    "submission_id": "CF104788892",
    "submission_url": "https://codeforces.com/contest/1474/submission/104788892",
    "tags": [
      "binary search",
      "constructive algorithms",
      "greedy",
      "math",
      "number theory",
      "*1000"
    ],
    "timestamp": "Jan/19/2021 20:29"
  },
  "CF104916318": {
    "contest_id": 1474,
    "language": "GNU C++17",
    "path": "codeforces/1474/C.cpp",
    "platform": "Codeforces",
    "problem_index": "C",
    "problem_name": "Array Destruction",
    "problem_url": "https://codeforces.com/contest/1474/problem/C",
    "submission_id": "CF104916318",
    "submission_url": "https://codeforces.com/contest/1474/submission/104916318",
    "tags": [
      "brute force",
      "constructive algorithms",
      "data structures",
      "greedy",
      "implementation",
      "sortings",
      "*1700"
    ],
    "timestamp": "Jan/20/2021 20:37"
  },
  "CF104964303": {
    "contest_id": 1352,
    "language": "GNU C++17",
    "path": "codeforces/1352/E.cpp",
    "platform": "Codeforces",
    "problem_index": "E",
    "problem_name": "Special Elements",
    "problem_url": "https://codeforces.com/contest/1352/problem/E",
    "submission_id": "CF104964303",
    "submission_url": "https://codeforces.com/contest/1352/submission/104964303",
    "tags": [
      "brute force",
      "implementation",
      "two pointers",
      "*1500"
    ],
    "timestamp": "Jan/21/2021 13:29"
  },
  "CF104968175": {
    "contest_id": 1296,
    "language": "GNU C++17",
    "path": "codeforces/1296/C.cpp",
    "platform": "Codeforces",
    "problem_index": "C",
    "problem_name": "Yet Another Walking Robot",
    "problem_url": "https://codeforces.com/contest/1296/problem/C",
    "submission_id": "CF104968175",
    "submission_url": "https://codeforces.com/contest/1296/submission/104968175",
    "tags": [
      "data structures",
      "implementation",
      "*1500"
    ],
    "timestamp": "Jan/21/2021 14:21"
  },
  "CF104971427": {
    "contest_id": 1340,
    "language": "GNU C++17",
    "path": "codeforces/1340/A.cpp",
    "platform": "Codeforces",
    "problem_index": "A",
    "problem_name": "Nastya and Strange Generator",
    "problem_url": "https://codeforces.com/contest/1340/problem/A",
    "submission_id": "CF104971427",
    "submission_url": "https://codeforces.com/contest/1340/submission/104971427",
    "tags": [
      "brute force",
      "data structures",
      "greedy",
      "implementation",
      "*1500"
    ],
    "timestamp": "Jan/21/2021 15:08"
  },
  "CF104984375": {
    "contest_id": 165,
    "language": "GNU C++17",
    "path": "codeforces/165/C.cpp",
    "platform": "Codeforces",
    "problem_index": "C",
    "problem_name": "Another Problem on Strings",
    "problem_url": "https://codeforces.com/contest/165/problem/C",
    "submission_id": "CF104984375",
    "submission_url": "https://codeforces.com/contest/165/submission/104984375",
    "tags": [
      "binary search",
      "brute force",
      "dp",
      "math",
      "strings",
      "two pointers",
      "*1600"
    ],
    "timestamp": "Jan/21/2021 17:59"
  },
  "CF104995292": {
    "contest_id": 1368,
    "language": "GNU C++17",
    "path": "codeforces/1368/C.cpp",
    "platform": "Codeforces",
    "problem_index": "C",
    "problem_name": "Even Picture",
    "problem_url": "https://codeforces.com/contest/1368/problem/C",
    "submission_id": "CF104995292",
    "submission_url": "https://codeforces.com/contest/1368/submission/104995292",
    "tags": [
      "constructive algorithms",
      "*1500"
    ],
    "timestamp": "Jan/21/2021 19:59"
  },
  "CF105001245": {
    "contest_id": 1304,
    "language": "GNU C++17",
    "path": "codeforces/1304/C.cpp",
    "platform": "Codeforces",
    "problem_index": "C",
    "problem_name": "Air Conditioner",
    "problem_url": "https://codeforces.com/contest/1304/problem/C",
    "submission_id": "CF105001245",
    "submission_url": "https://codeforces.com/contest/1304/submission/105001245",
    "tags": [
      "dp",
      "greedy",
      "implementation",
      "sortings",
      "two pointers",
      "*1500"
    ],
    "timestamp": "Jan/21/2021 21:04"
  },
  "CF105015403": {
    "contest_id": 1461,
    "language": "GNU C++17",
    "path": "codeforces/1461/D.cpp",
    "platform": "Codeforces",
    "problem_index": "D",
    "problem_name": "Divide and Summarize",
    "problem_url": "https://codeforces.com/contest/1461/problem/D",
    "submission_id": "CF105015403",
    "submission_url": "https://codeforces.com/contest/1461/submission/105015403",
    "tags": [
      "binary search",
      "brute force",
      "data structures",
      "divide and conquer",
      "implementation",
      "sortings",
      "*1600"
    ],
    "timestamp": "Jan/22/2021 00:12"
  },
  "CF105138523": {
    "contest_id": 1385,
    "language": "GNU C++17",
    "path": "codeforces/1385/D.cpp",
    "platform": "Codeforces",
    "problem_index": "D",
    "problem_name": "a-Good String",
    "problem_url": "https://codeforces.com/contest/1385/problem/D",
    "submission_id": "CF105138523",
    "submission_url": "https://codeforces.com/contest/1385/submission/105138523",
    "tags": [
      "bitmasks",
      "brute force",
      "divide and conquer",
      "dp",
      "implementation",
      "*1500"
    ],
    "timestamp": "Jan/23/2021 15:11"
  },
  "CF105179055": {
    "contest_id": 144,
    "language": "PyPy 3",
    "path": "codeforces/144/A.py",
    "platform": "Codeforces",
    "problem_index": "A",
    "problem_name": "Arrival of the General",
    "problem_url": "https://codeforces.com/contest/144/problem/A",
    "submission_id": "CF105179055",
    "submission_url": "https://codeforces.com/contest/144/submission/105179055",
    "tags": [
      "implementation",
      "*800"
    ],
    "timestamp": "Jan/24/2021 01:12"
  },
  "CF105538106": {
    "contest_id": 676,
    "language": "GNU C++17",
    "path": "codeforces/676/C.cpp",
    "platform": "Codeforces",
    "problem_index": "C",
    "problem_name": "Vasya and String",
    "problem_url": "https://codeforces.com/contest/676/problem/C",
    "submission_id": "CF105538106",
    "submission_url": "https://codeforces.com/contest/676/submission/105538106",
    "tags": [
      "binary search",
      "dp",
      "strings",
      "two pointers",
      "*1500"
    ],
    "timestamp": "Jan/27/2021 11:40"
  },
  "CF105546971": {
    "contest_id": 1466,
    "language": "GNU C++17",
    "path": "codeforces/1466/E.cpp",
    "platform": "Codeforces",
    "problem_index": "E",
    "problem_name": "Apollo versus Pan",
    "problem_url": "https://codeforces.com/contest/1466/problem/E",
    "submission_id": "CF105546971",
    "submission_url": "https://codeforces.com/contest/1466/submission/105546971",
    "tags": [
      "bitmasks",
      "brute force",
      "math",
      "*1800"
    ],
    "timestamp": "Jan/27/2021 13:23"
  },
  "CF105551019": {
    "contest_id": 1163,
    "language": "GNU C++17",
    "path": "codeforces/1163/B1.cpp",
    "platform": "Codeforces",
    "problem_index": "B1",
    "problem_name": "Cat Party (Easy Edition)",
    "problem_url": "https://codeforces.com/contest/1163/problem/B1",
    "submission_id": "CF105551019",
    "submission_url": "https://codeforces.com/contest/1163/submission/105551019",
    "tags": [
      "data structures",
      "implementation",
      "*1500"
    ],
    "timestamp": "Jan/27/2021 14:14"
  },
  "CF105637725": {
    "contest_id": 1475,
    "language": "GNU C++17",
    "path": "codeforces/1475/A.cpp",
    "platform": "Codeforces",
    "problem_index": "A",
    "problem_name": "Odd Divisor",
    "problem_url": "https://codeforces.com/contest/1475/problem/A",
    "submission_id": "CF105637725",
    "submission_url": "https://codeforces.com/contest/1475/submission/105637725",
    "tags": [
      "math",
      "number theory",
      "*900"
    ],
    "timestamp": "Jan/28/2021 12:01"
  },
  "CF105638317": {
    "contest_id": 1475,
    "language": "GNU C++17",
    "path": "codeforces/1475/B.cpp",
    "platform": "Codeforces",
    "problem_index": "B",
    "problem_name": "New Year's Number",
    "problem_url": "https://codeforces.com/contest/1475/problem/B",
    "submission_id": "CF105638317",
    "submission_url": "https://codeforces.com/contest/1475/submission/105638317",
    "tags": [
      "brute force",
      "dp",
      "math",
      "*900"
    ],
    "timestamp": "Jan/28/2021 12:09"
  },
  "CF105639831": {
    "contest_id": 1475,
    "language": "GNU C++17",
    "path": "codeforces/1475/C.cpp",
    "platform": "Codeforces",
    "problem_index": "C",
    "problem_name": "Ball in Berland",
    "problem_url": "https://codeforces.com/contest/1475/problem/C",
    "submission_id": "CF105639831",
    "submission_url": "https://codeforces.com/contest/1475/submission/105639831",
    "tags": [
      "combinatorics",
      "graphs",
      "math",
      "*1400"
    ],
    "timestamp": "Jan/28/2021 12:27"
  },
  "CF105641921": {
    "contest_id": 1475,
    "language": "GNU C++17",
    "path": "codeforces/1475/E.cpp",
    "platform": "Codeforces",
    "problem_index": "E",
    "problem_name": "Advertising Agency",
    "problem_url": "https://codeforces.com/contest/1475/problem/E",
    "submission_id": "CF105641921",
    "submission_url": "https://codeforces.com/contest/1475/submission/105641921",
    "tags": [
      "combinatorics",
      "math",
      "sortings",
      "*1600"
    ],
    "timestamp": "Jan/28/2021 12:51"
  },
  "CF105680383": {
    "contest_id": 1478,
    "language": "GNU C++17",
    "path": "codeforces/1478/A.cpp",
    "platform": "Codeforces",
    "problem_index": "A",
    "problem_name": "Nezzar and Colorful Balls",
    "problem_url": "https://codeforces.com/contest/1478/problem/A",
    "submission_id": "CF105680383",
    "submission_url": "https://codeforces.com/contest/1478/submission/105680383",
    "tags": [
      "brute force",
      "greedy",
      "*800"
    ],
    "timestamp": "Jan/28/2021 20:09"
  },
  "CF105703063": {
    "contest_id": 1478,
    "language": "GNU C++17",
    "path": "codeforces/1478/B.cpp",
    "platform": "Codeforces",
    "problem_index": "B",
    "problem_name": "Nezzar and Lucky Number",
    "problem_url": "https://codeforces.com/contest/1478/problem/B",
    "submission_id": "CF105703063",
    "submission_url": "https://codeforces.com/contest/1478/submission/105703063",
    "tags": [
      "brute force",
      "dp",
      "greedy",
      "math",
      "*1100"
    ],
    "timestamp": "Jan/28/2021 20:35"
  },
  "CF105785582": {
    "contest_id": 1478,
    "language": "GNU C++17",
    "path": "codeforces/1478/C.cpp",
    "platform": "Codeforces",
    "problem_index": "C",
    "problem_name": "Nezzar and Symmetric Array",
    "problem_url": "https://codeforces.com/contest/1478/problem/C",
    "submission_id": "CF105785582",
    "submission_url": "https://codeforces.com/contest/1478/submission/105785582",
    "tags": [
      "implementation",
      "math",
      "sortings",
      "*1700"
    ],
    "timestamp": "Jan/29/2021 01:56"
  },
  "CF105860645": {
    "contest_id": 1476,
    "language": "GNU C++17",
    "path": "codeforces/1476/A.cpp",
    "platform": "Codeforces",
    "problem_index": "A",
    "problem_name": "K-divisible Sum",
    "problem_url": "https://codeforces.com/contest/1476/problem/A",
    "submission_id": "CF105860645",
    "submission_url": "https://codeforces.com/contest/1476/submission/105860645",
    "tags": [
      "binary search",
      "constructive algorithms",
      "greedy",
      "math",
      "*1000"
    ],
    "timestamp": "Jan/29/2021 20:15"
  },
  "CF105931892": {
    "contest_id": 1476,
    "language": "GNU C++17",
    "path": "codeforces/1476/B.cpp",
    "platform": "Codeforces",
    "problem_index": "B",
    "problem_name": "Inflation",
    "problem_url": "https://codeforces.com/contest/1476/problem/B",
    "submission_id": "CF105931892",
    "submission_url": "https://codeforces.com/contest/1476/submission/105931892",
    "tags": [
      "binary search",
      "brute force",
      "greedy",
      "math",
      "*1300"
    ],
    "timestamp": "Jan/29/2021 21:52"
  },
  "CF106035280": {
    "contest_id": 1373,
    "language": "GNU C++17",
    "path": "codeforces/1373/B.cpp",
    "platform": "Codeforces",
    "problem_index": "B",
    "problem_name": "01 Game",
    "problem_url": "https://codeforces.com/contest/1373/problem/B",
    "submission_id": "CF106035280",
    "submission_url": "https://codeforces.com/contest/1373/submission/106035280",
    "tags": [
      "games",
      "*900"
    ],
    "timestamp": "Jan/30/2021 21:10"
  },
  "CF106107405": {
    "contest_id": 1476,
    "language": "GNU C++17",
    "path": "codeforces/1476/C.cpp",
    "platform": "Codeforces",
    "problem_index": "C",
    "problem_name": "Longest Simple Cycle",
    "problem_url": "https://codeforces.com/contest/1476/problem/C",
    "submission_id": "CF106107405",
    "submission_url": "https://codeforces.com/contest/1476/submission/106107405",
    "tags": [
      "dp",
      "graphs",
      "greedy",
      "*1600"
    ],
    "timestamp": "Jan/31/2021 19:11"
  },
  "CF106110866": {
    "contest_id": 1476,
    "language": "GNU C++17",
    "path": "codeforces/1476/D.cpp",
    "platform": "Codeforces",
    "problem_index": "D",
    "problem_name": "Journey",
    "problem_url": "https://codeforces.com/contest/1476/problem/D",
    "submission_id": "CF106110866",
    "submission_url": "https://codeforces.com/contest/1476/submission/106110866",
    "tags": [
      "dfs and similar",
      "dp",
      "dsu",
      "implementation",
      "*1700"
    ],
    "timestamp": "Jan/31/2021 19:50"
  },
  "CF106119483": {
    "contest_id": 1475,
    "language": "GNU C++17",
    "path": "codeforces/1475/D.cpp",
    "platform": "Codeforces",
    "problem_index": "D",
    "problem_name": "Cleaning the Phone",
    "problem_url": "https://codeforces.com/contest/1475/problem/D",
    "submission_id": "CF106119483",
    "submission_url": "https://codeforces.com/contest/1475/submission/106119483",
    "tags": [
      "binary search",
      "dp",
      "sortings",
      "two pointers",
      "*1800"
    ],
    "timestamp": "Jan/31/2021 21:26"
  },
  "CF106166873": {
    "contest_id": 466,
    "language": "GNU C++17",
    "path": "codeforces/466/B.cpp",
    "platform": "Codeforces",
    "problem_index": "B",
    "problem_name": "Wonder Room",
    "problem_url": "https://codeforces.com/contest/466/problem/B",
    "submission_id": "CF106166873",
    "submission_url": "https://codeforces.com/contest/466/submission/106166873",
    "tags": [
      "brute force",
      "math",
      "*2000"
    ],
    "timestamp": "Feb/01/2021 13:25"
  },
  "CF106169467": {
    "contest_id": 466,
    "language": "GNU C++17",
    "path": "codeforces/466/B.cpp",
    "platform": "Codeforces",
    "problem_index": "B",
    "problem_name": "Wonder Room",
    "problem_url": "https://codeforces.com/contest/466/problem/B",
    "submission_id": "CF106169467",
    "submission_url": "https://codeforces.com/contest/466/submission/106169467",
    "tags": [
      "brute force",
      "math",
      "*2000"
    ],
    "timestamp": "Feb/01/2021 13:59"
  },
  "CF106271122": {
    "contest_id": 560,
    "language": "GNU C++17",
    "path": "codeforces/560/C.cpp",
    "platform": "Codeforces",
    "problem_index": "C",
    "problem_name": "Gerald's Hexagon",
    "problem_url": "https://codeforces.com/contest/560/problem/C",
    "submission_id": "CF106271122",
    "submission_url": "https://codeforces.com/contest/560/submission/106271122",
    "tags": [
      "geometry",
      "*1600"
    ],
    "timestamp": "Feb/02/2021 16:12"
  },
  "CF106343762": {
    "contest_id": 1477,
    "language": "GNU C++17",
    "path": "codeforces/1477/A.cpp",
    "platform": "Codeforces",
    "problem_index": "A",
    "problem_name": "Nezzar and Board",
    "problem_url": "https://codeforces.com/contest/1477/problem/A",
    "submission_id": "CF106343762",
    "submission_url": "https://codeforces.com/contest/1477/submission/106343762",
    "tags": [
      "constructive algorithms",
      "math",
      "number theory",
      "*1800"
    ],
    "timestamp": "Feb/03/2021 12:47"
  }
}